acapela_box/__init__.py
acapela_box/__main__.py
acapela_box/base.py
acapela_box/data.py
acapela_box-1.3.dist-info/LICENSE
acapela_box-1.3.dist-info/METADATA
acapela_box-1.3.dist-info/WHEEL
acapela_box-1.3.dist-info/entry_points.txt
acapela_box-1.3.dist-info/top_level.txt
acapela_box-1.3.dist-info/RECORD
