Metadata-Version: 2.1
Name: acapela-box
Version: 1.3
Summary: Fetch generated tts sounds from Acapela Group.
Home-page: https://github.com/alekssamos/acapela_box/
Author: alekssamos
Author-email: aleks-samos@yandex.ru
License: UNKNOWN
Platform: UNKNOWN
License-File: LICENSE
Requires-Dist: click
Requires-Dist: requests
